fate/__init__.py
fate/__main__.py
fate/cli/__init__.py
fate/cli/__main__.py
fate/cli/base/__init__.py
fate/cli/base/common.py
fate/cli/base/execution.py
fate/cli/base/main.py
fate/cli/command/__init__.py
fate/cli/command/control.py
fate/cli/command/debug.py
fate/cli/command/init.py
fate/cli/include/banner/broadway
fate/cli/include/banner/fire-font-k
fate/cli/include/banner/larry-3d
fate/cli/root.py
fate/common/__init__.py
fate/common/ext.py
fate/common/log.py
fate/common/output.py
fate/conf/__init__.py
fate/conf/base/__init__.py
fate/conf/base/conf.py
fate/conf/base/conf_group.py
fate/conf/error.py
fate/conf/include/defaults.toml
fate/conf/include/defaults.yaml
fate/conf/include/tasks.toml
fate/conf/include/tasks.yaml
fate/conf/path.py
fate/conf/schema.py
fate/conf/template.py
fate/conf/types/__init__.py
fate/conf/types/base.py
fate/conf/types/default.py
fate/conf/types/task.py
fate/sched/__init__.py
fate/sched/base/__init__.py
fate/sched/base/pool.py
fate/sched/base/scheduler.py
fate/sched/base/state.py
fate/sched/base/task/__init__.py
fate/sched/base/task/ext.py
fate/sched/base/task/invoked_task/__init__.py
fate/sched/base/task/invoked_task/base.py
fate/sched/base/task/invoked_task/event.py
fate/sched/base/task/invoked_task/failed_task.py
fate/sched/base/task/invoked_task/spawned_task.py
fate/sched/base/task/scheduled_task.py
fate/sched/base/timing.py
fate/sched/base/util/__init__.py
fate/sched/base/util/reset.py
fate/sched/tiered_tenancy.py
fate/sys/platform/include/systemd/fate.service
fate/task/__init__.py
fate/task/log.py
fate/task/param.py
fate/task/result.py
fate/task/state/__init__.py
fate/task/state/self.py
fate/util/__init__.py
fate/util/abstract.py
fate/util/animals.py
fate/util/argument.py
fate/util/compat/__init__.py
fate/util/compat/argument.py
fate/util/compat/os.py
fate/util/compat/path.py
fate/util/compat/resources.py
fate/util/compat/types.py
fate/util/datastructure/__init__.py
fate/util/datastructure/access.py
fate_scheduler-1.1.0.dist-info/METADATA
fate_scheduler-1.1.0.dist-info/WHEEL
fate_scheduler-1.1.0.dist-info/entry_points.txt
fate_scheduler-1.1.0.dist-info/RECORD
