Metadata-Version: 2.3
Name: fate-scheduler
Version: 1.1.0
Summary: The operating system-level command scheduler and manager.
Home-page: https://github.com/chicago-cdac/fate
License: MIT
Author: Jesse London
Author-email: jesselondon@gmail.com
Requires-Python: >=3.8,<4.0
Classifier: License :: OSI Approved :: MIT License
Classifier: Programming Language :: Python :: 3
Classifier: Programming Language :: Python :: 3.8
Classifier: Programming Language :: Python :: 3.9
Classifier: Programming Language :: Python :: 3.10
Classifier: Programming Language :: Python :: 3.11
Classifier: Programming Language :: Python :: 3.12
Classifier: Programming Language :: Python :: 3.13
Requires-Dist: Dickens (>=2.1,<3.0)
Requires-Dist: Jinja2 (>=3.1.2,<4.0.0)
Requires-Dist: argcmdr (>=1.0.1,<2.0.0)
Requires-Dist: argcomplete (>=2.0,<3.0)
Requires-Dist: croniter (>=1.3.5,<2.0.0)
Requires-Dist: importlib-resources (==5.0) ; python_version >= "3.8" and python_version < "3.10"
Requires-Dist: lmdb-dict-full (>=1.0.2)
Requires-Dist: loguru (>=0.6.0,<0.7.0)
Requires-Dist: pyyaml (>=6.0,<7.0)
Requires-Dist: schema (>=0.7.5,<0.8.0)
Requires-Dist: toml (>=0.10.2,<0.11.0)
Requires-Dist: wcwidth (>=0.2.5,<0.3.0)
Project-URL: Repository, https://github.com/chicago-cdac/fate
